{
  "gitSyncId": "6809e4f23a27664fff0929ff_5fc13818-4e4f-43a1-b339-850d4835bf99",
  "id": "Orders_utils.generateInvoice",
  "pluginId": "js-plugin",
  "pluginType": "JS",
  "unpublishedAction": {
    "actionConfiguration": {
      "encodeParamsToggle": true,
      "isAsync": true,
      "jsArguments": [],
      "paginationType": "NONE",
      "timeoutInMillisecond": 10000
    },
    "collectionId": "Orders_utils",
    "confirmBeforeExecute": false,
    "datasource": {
      "isAutoGenerated": false,
      "name": "UNUSED_DATASOURCE",
      "pluginId": "js-plugin"
    },
    "dynamicBindingPathList": [
      {
        "key": "body"
      }
    ],
    "fullyQualifiedName": "utils.generateInvoice",
    "name": "generateInvoice",
    "pageId": "Orders",
    "runBehaviour": "MANUAL",
    "userSetOnLoad": false
  }
}